pyhtml5/__init__.py
pyhtml5/__init__.pyi
pyhtml5/css.py
pyhtml5/html.py
pyhtml5/py.typed
pyhtml5/utils.py
pyhtml5-0.0.6.dist-info/licenses/LICENSE
pyhtml5-0.0.6.dist-info/METADATA
pyhtml5-0.0.6.dist-info/WHEEL
pyhtml5-0.0.6.dist-info/top_level.txt
pyhtml5-0.0.6.dist-info/RECORD
