Metadata-Version: 2.4
Name: pyhtml5
Version: 0.0.6
Summary: A small library for generating HTML & CSS using Python syntax.
Requires-Python: >=3.9
License-File: LICENSE
Dynamic: license-file
